Metadata-Version: 2.1
Name: pyequion
Version: 0.0.5.5
Summary: Chemical equilibrium for electrolytes in pure python
Home-page: https://github.com/caiofcm/pyequion
Author: Caio Curitiba Marcellos
Author-email: caiocuritiba@gmail.com
License: BSD 3-Clause
Keywords: scientific,chemical equilibrium
Platform: UNKNOWN
Classifier: Intended Audience :: Science/Research
Classifier: License :: OSI Approved :: BSD License
Classifier: Natural Language :: English
Classifier: Operating System :: OS Independent
Classifier: Programming Language :: Python :: 3
Classifier: Programming Language :: Python :: 3.7
Classifier: Programming Language :: Python :: 3.8
Classifier: Topic :: Scientific/Engineering
